Workbook

Sheet DASHBOARD
A1: 📊 CRM DASHBOARD - ЦЕНТР УПРАВЛЕНИЯ ПРОДАЖАМИ
A3: 📈 КЛЮЧЕВЫЕ ПОКАЗАТЕЛИ - ОБЩАЯ СТАТИСТИКА
B5: ЛИДЫ | E5: НЕ ДОЗВОН | H5: ОЖИДАНИЕ | K5: ОТКАЗ | N5: 🎯 ПРОДАЖИ
B6: =SUM(B18:B37) | E6: =SUM(D18:D37) | H6: =SUM(E18:E37) | K6: =SUM(F18:F37) | N6: =SUM(G18:G37)
A10: 💰 ВЫРУЧКА | E10: 📊 КОНВЕРСИЯ | I10: 💵 СРЕДНИЙ ЧЕК | M10: 💰 ОБЩИЙ ОСТАТОК
A11: =SUM(I18:I37) | E11: =IF(B6=0,0,N6/B6*100) | I11: =IF(N6=0,0,A11/N6) | M11: =SUM(K18:K37)
A16: 👥 СВОДНАЯ СТАТИСТИКА ПО МЕНЕДЖЕРАМ
A17: Менеджер | B17: Лиды | C17: Обработка | D17: Не дозвон | E17: Ожидание | F17: Отказ | G17: Продажи | H17: Конверсия | I17: Выручка | J17: Ср. чек | K17: Остаток | L17: Рейтинг
A18: Менеджер 1 | B18: =Mgr_1!AG4 | C18: =Mgr_1!AG5 | D18: =Mgr_1!AG6 | E18: =Mgr_1!AG7 | F18: =Mgr_1!AG8 | G18: =Mgr_1!AG9 | H18: =Mgr_1!AG11 | I18: =Mgr_1!AG10 | J18: =IF(G18=0,0,I18/G18) | K18: =Mgr_1!AG12 | L18: =RANK(I18,I$18:I$37,0)
A19: Менеджер 2 | B19: =Mgr_2!AG4 | C19: =Mgr_2!AG5 | D19: =Mgr_2!AG6 | E19: =Mgr_2!AG7 | F19: =Mgr_2!AG8 | G19: =Mgr_2!AG9 | H19: =Mgr_2!AG11 | I19: =Mgr_2!AG10 | J19: =IF(G19=0,0,I19/G19) | K19: =Mgr_2!AG12 | L19: =RANK(I19,I$18:I$37,0)
A20: Менеджер 3 | B20: =Mgr_3!AG4 | C20: =Mgr_3!AG5 | D20: =Mgr_3!AG6 | E20: =Mgr_3!AG7 | F20: =Mgr_3!AG8 | G20: =Mgr_3!AG9 | H20: =Mgr_3!AG11 | I20: =Mgr_3!AG10 | J20: =IF(G20=0,0,I20/G20) | K20: =Mgr_3!AG12 | L20: =RANK(I20,I$18:I$37,0)
A21: Менеджер 4 | B21: =Mgr_4!AG4 | C21: =Mgr_4!AG5 | D21: =Mgr_4!AG6 | E21: =Mgr_4!AG7 | F21: =Mgr_4!AG8 | G21: =Mgr_4!AG9 | H21: =Mgr_4!AG11 | I21: =Mgr_4!AG10 | J21: =IF(G21=0,0,I21/G21) | K21: =Mgr_4!AG12 | L21: =RANK(I21,I$18:I$37,0)
A22: Менеджер 5 | B22: =Mgr_5!AG4 | C22: =Mgr_5!AG5 | D22: =Mgr_5!AG6 | E22: =Mgr_5!AG7 | F22: =Mgr_5!AG8 | G22: =Mgr_5!AG9 | H22: =Mgr_5!AG11 | I22: =Mgr_5!AG10 | J22: =IF(G22=0,0,I22/G22) | K22: =Mgr_5!AG12 | L22: =RANK(I22,I$18:I$37,0)
A23: Менеджер 6 | B23: =Mgr_6!AG4 | C23: =Mgr_6!AG5 | D23: =Mgr_6!AG6 | E23: =Mgr_6!AG7 | F23: =Mgr_6!AG8 | G23: =Mgr_6!AG9 | H23: =Mgr_6!AG11 | I23: =Mgr_6!AG10 | J23: =IF(G23=0,0,I23/G23) | K23: =Mgr_6!AG12 | L23: =RANK(I23,I$18:I$37,0)
A24: Менеджер 7 | B24: =Mgr_7!AG4 | C24: =Mgr_7!AG5 | D24: =Mgr_7!AG6 | E24: =Mgr_7!AG7 | F24: =Mgr_7!AG8 | G24: =Mgr_7!AG9 | H24: =Mgr_7!AG11 | I24: =Mgr_7!AG10 | J24: =IF(G24=0,0,I24/G24) | K24: =Mgr_7!AG12 | L24: =RANK(I24,I$18:I$37,0)
A25: Менеджер 8 | B25: =Mgr_8!AG4 | C25: =Mgr_8!AG5 | D25: =Mgr_8!AG6 | E25: =Mgr_8!AG7 | F25: =Mgr_8!AG8 | G25: =Mgr_8!AG9 | H25: =Mgr_8!AG11 | I25: =Mgr_8!AG10 | J25: =IF(G25=0,0,I25/G25) | K25: =Mgr_8!AG12 | L25: =RANK(I25,I$18:I$37,0)
A26: Менеджер 9 | B26: =Mgr_9!AG4 | C26: =Mgr_9!AG5 | D26: =Mgr_9!AG6 | E26: =Mgr_9!AG7 | F26: =Mgr_9!AG8 | G26: =Mgr_9!AG9 | H26: =Mgr_9!AG11 | I26: =Mgr_9!AG10 | J26: =IF(G26=0,0,I26/G26) | K26: =Mgr_9!AG12 | L26: =RANK(I26,I$18:I$37,0)
A27: Менеджер 10 | B27: =Mgr_10!AG4 | C27: =Mgr_10!AG5 | D27: =Mgr_10!AG6 | E27: =Mgr_10!AG7 | F27: =Mgr_10!AG8 | G27: =Mgr_10!AG9 | H27: =Mgr_10!AG11 | I27: =Mgr_10!AG10 | J27: =IF(G27=0,0,I27/G27) | K27: =Mgr_10!AG12 | L27: =RANK(I27,I$18:I$37,0)
A28: Менеджер 11 | B28: =Mgr_11!AG4 | C28: =Mgr_11!AG5 | D28: =Mgr_11!AG6 | E28: =Mgr_11!AG7 | F28: =Mgr_11!AG8 | G28: =Mgr_11!AG9 | H28: =Mgr_11!AG11 | I28: =Mgr_11!AG10 | J28: =IF(G28=0,0,I28/G28) | K28: =Mgr_11!AG12 | L28: =RANK(I28,I$18:I$37,0)
A29: Менеджер 12 | B29: =Mgr_12!AG4 | C29: =Mgr_12!AG5 | D29: =Mgr_12!AG6 | E29: =Mgr_12!AG7 | F29: =Mgr_12!AG8 | G29: =Mgr_12!AG9 | H29: =Mgr_12!AG11 | I29: =Mgr_12!AG10 | J29: =IF(G29=0,0,I29/G29) | K29: =Mgr_12!AG12 | L29: =RANK(I29,I$18:I$37,0)
A30: Менеджер 13 | B30: =Mgr_13!AG4 | C30: =Mgr_13!AG5 | D30: =Mgr_13!AG6 | E30: =Mgr_13!AG7 | F30: =Mgr_13!AG8 | G30: =Mgr_13!AG9 | H30: =Mgr_13!AG11 | I30: =Mgr_13!AG10 | J30: =IF(G30=0,0,I30/G30) | K30: =Mgr_13!AG12 | L30: =RANK(I30,I$18:I$37,0)
A31: Менеджер 14 | B31: =Mgr_14!AG4 | C31: =Mgr_14!AG5 | D31: =Mgr_14!AG6 | E31: =Mgr_14!AG7 | F31: =Mgr_14!AG8 | G31: =Mgr_14!AG9 | H31: =Mgr_14!AG11 | I31: =Mgr_14!AG10 | J31: =IF(G31=0,0,I31/G31) | K31: =Mgr_14!AG12 | L31: =RANK(I31,I$18:I$37,0)
A32: Менеджер 15 | B32: =Mgr_15!AG4 | C32: =Mgr_15!AG5 | D32: =Mgr_15!AG6 | E32: =Mgr_15!AG7 | F32: =Mgr_15!AG8 | G32: =Mgr_15!AG9 | H32: =Mgr_15!AG11 | I32: =Mgr_15!AG10 | J32: =IF(G32=0,0,I32/G32) | K32: =Mgr_15!AG12 | L32: =RANK(I32,I$18:I$37,0)
A33: Менеджер 16 | B33: =Mgr_16!AG4 | C33: =Mgr_16!AG5 | D33: =Mgr_16!AG6 | E33: =Mgr_16!AG7 | F33: =Mgr_16!AG8 | G33: =Mgr_16!AG9 | H33: =Mgr_16!AG11 | I33: =Mgr_16!AG10 | J33: =IF(G33=0,0,I33/G33) | K33: =Mgr_16!AG12 | L33: =RANK(I33,I$18:I$37,0)
A34: Менеджер 17 | B34: =Mgr_17!AG4 | C34: =Mgr_17!AG5 | D34: =Mgr_17!AG6 | E34: =Mgr_17!AG7 | F34: =Mgr_17!AG8 | G34: =Mgr_17!AG9 | H34: =Mgr_17!AG11 | I34: =Mgr_17!AG10 | J34: =IF(G34=0,0,I34/G34) | K34: =Mgr_17!AG12 | L34: =RANK(I34,I$18:I$37,0)
A35: Менеджер 18 | B35: =Mgr_18!AG4 | C35: =Mgr_18!AG5 | D35: =Mgr_18!AG6 | E35: =Mgr_18!AG7 | F35: =Mgr_18!AG8 | G35: =Mgr_18!AG9 | H35: =Mgr_18!AG11 | I35: =Mgr_18!AG10 | J35: =IF(G35=0,0,I35/G35) | K35: =Mgr_18!AG12 | L35: =RANK(I35,I$18:I$37,0)
A36: Менеджер 19 | B36: =Mgr_19!AG4 | C36: =Mgr_19!AG5 | D36: =Mgr_19!AG6 | E36: =Mgr_19!AG7 | F36: =Mgr_19!AG8 | G36: =Mgr_19!AG9 | H36: =Mgr_19!AG11 | I36: =Mgr_19!AG10 | J36: =IF(G36=0,0,I36/G36) | K36: =Mgr_19!AG12 | L36: =RANK(I36,I$18:I$37,0)
A37: Менеджер 20 | B37: =Mgr_20!AG4 | C37: =Mgr_20!AG5 | D37: =Mgr_20!AG6 | E37: =Mgr_20!AG7 | F37: =Mgr_20!AG8 | G37: =Mgr_20!AG9 | H37: =Mgr_20!AG11 | I37: =Mgr_20!AG10 | J37: =IF(G37=0,0,I37/G37) | K37: =Mgr_20!AG12 | L37: =RANK(I37,I$18:I$37,0)
A38: ИТОГО | B38: =SUM(B18:B37) | C38: =SUM(C18:C37) | D38: =SUM(D18:D37) | E38: =SUM(E18:E37) | F38: =SUM(F18:F37) | G38: =SUM(G18:G37) | H38: =IF(B38=0,0,G38/B38*100) | I38: =SUM(I18:I37) | J38: =IF(G38=0,0,I38/G38) | K38: =SUM(K18:K37) | L38: -
A41: 🏆 РЕЙТИНГ ПРОДАВЦОВ
B43: 📅 ПО ДНЯМ ▼ | F43: 📆 ПО НЕДЕЛЯМ | J43: 📊 ПО МЕСЯЦАМ
A45: 📅 РЕЙТИНГ ПО ДНЯМ МЕСЯЦА (ВЫРУЧКА)
A46: Менеджер | B46: 02 | C46: 03 | D46: 04 | E46: 05 | F46: 06 | G46: 07 | H46: 08 | I46: 09 | J46: 10 | K46: 11 | L46: 12 | M46: 13 | N46: 14 | O46: 15 | P46: 16 | Q46: 17 | R46: 17 | S46: 18 | T46: 19 | U46: 20 | V46: 21 | W46: 22 | X46: 23 | Y46: 24 | Z46: 25 | AA46: 26 | AB46: 27 | AC46: 28 | AD46: 29 | AE46: 30 | AF46: 31
A47: Менеджер 1 | B47: =Mgr_1!B10 | C47: =Mgr_1!C10 | D47: =Mgr_1!D10 | E47: =Mgr_1!E10 | F47: =Mgr_1!F10 | G47: =Mgr_1!G10 | H47: =Mgr_1!H10 | I47: =Mgr_1!I10 | ... AF47: =Mgr_1!AF10
A48: Менеджер 2 | B48: =Mgr_2!B10 | C48: =Mgr_2!C10 | D48: =Mgr_2!D10 | E48: =Mgr_2!E10 | F48: =Mgr_2!F10 | G48: =Mgr_2!G10 | H48: =Mgr_2!H10 | I48: =Mgr_2!I10 | ... AF48: =Mgr_2!AF10
A49: Менеджер 3 | B49: =Mgr_3!B10 | C49: =Mgr_3!C10 | D49: =Mgr_3!D10 | E49: =Mgr_3!E10 | F49: =Mgr_3!F10 | G49: =Mgr_3!G10 | H49: =Mgr_3!H10 | I49: =Mgr_3!I10 | ... AF49: =Mgr_3!AF10
A50: Менеджер 4 | B50: =Mgr_4!B10 | C50: =Mgr_4!C10 | D50: =Mgr_4!D10 | E50: =Mgr_4!E10 | F50: =Mgr_4!F10 | G50: =Mgr_4!G10 | H50: =Mgr_4!H10 | I50: =Mgr_4!I10 | ... AF50: =Mgr_4!AF10
A51: Менеджер 5 | B51: =Mgr_5!B10 | C51: =Mgr_5!C10 | D51: =Mgr_5!D10 | E51: =Mgr_5!E10 | F51: =Mgr_5!F10 | G51: =Mgr_5!G10 | H51: =Mgr_5!H10 | I51: =Mgr_5!I10 | ... AF51: =Mgr_5!AF10
A52: Менеджер 6 | B52: =Mgr_6!B10 | C52: =Mgr_6!C10 | D52: =Mgr_6!D10 | E52: =Mgr_6!E10 | F52: =Mgr_6!F10 | G52: =Mgr_6!G10 | H52: =Mgr_6!H10 | I52: =Mgr_6!I10 | ... AF52: =Mgr_6!AF10
A53: Менеджер 7 | B53: =Mgr_7!B10 | C53: =Mgr_7!C10 | D53: =Mgr_7!D10 | E53: =Mgr_7!E10 | F53: =Mgr_7!F10 | G53: =Mgr_7!G10 | H53: =Mgr_7!H10 | I53: =Mgr_7!I10 | ... AF53: =Mgr_7!AF10
A54: Менеджер 8 | B54: =Mgr_8!B10 | C54: =Mgr_8!C10 | D54: =Mgr_8!D10 | E54: =Mgr_8!E10 | F54: =Mgr_8!F10 | G54: =Mgr_8!G10 | H54: =Mgr_8!H10 | I54: =Mgr_8!I10 | ... AF54: =Mgr_8!AF10
A55: Менеджер 9 | B55: =Mgr_9!B10 | C55: =Mgr_9!C10 | D55: =Mgr_9!D10 | E55: =Mgr_9!E10 | F55: =Mgr_9!F10 | G55: =Mgr_9!G10 | H55: =Mgr_9!H10 | I55: =Mgr_9!I10 | ... AF55: =Mgr_9!AF10
A56: Менеджер 10 | B56: =Mgr_10!B10 | C56: =Mgr_10!C10 | D56: =Mgr_10!D10 | E56: =Mgr_10!E10 | F56: =Mgr_10!F10 | G56: =Mgr_10!G10 | H56: =Mgr_10!H10 | I56: =Mgr_10!I10 | ... AF56: =Mgr_10!AF10
A57: Менеджер 11 | B57: =Mgr_11!B10 | C57: =Mgr_11!C10 | D57: =Mgr_11!D10 | E57: =Mgr_11!E10 | F57: =Mgr_11!F10 | G57: =Mgr_11!G10 | H57: =Mgr_11!H10 | I57: =Mgr_11!I10 | ... AF57: =Mgr_11!AF10
A58: Менеджер 12 | B58: =Mgr_12!B10 | C58: =Mgr_12!C10 | D58: =Mgr_12!D10 | E58: =Mgr_12!E10 | F58: =Mgr_12!F10 | G58: =Mgr_12!G10 | H58: =Mgr_12!H10 | I58: =Mgr_12!I10 | ... AF58: =Mgr_12!AF10
A59: Менеджер 13 | B59: =Mgr_13!B10 | C59: =Mgr_13!C10 | D59: =Mgr_13!D10 | E59: =Mgr_13!E10 | F59: =Mgr_13!F10 | G59: =Mgr_13!G10 | H59: =Mgr_13!H10 | I59: =Mgr_13!I10 | ... AF59: =Mgr_13!AF10
A60: Менеджер 14 | B60: =Mgr_14!B10 | C60: =Mgr_14!C10 | D60: =Mgr_14!D10 | E60: =Mgr_14!E10 | F60: =Mgr_14!F10 | G60: =Mgr_14!G10 | H60: =Mgr_14!H10 | I60: =Mgr_14!I10 | ... AF60: =Mgr_14!AF10
A61: Менеджер 15 | B61: =Mgr_15!B10 | C61: =Mgr_15!C10 | D61: =Mgr_15!D10 | E61: =Mgr_15!E10 | F61: =Mgr_15!F10 | G61: =Mgr_15!G10 | H61: =Mgr_15!H10 | I61: =Mgr_15!I10 | ... AF61: =Mgr_15!AF10
A62: Менеджер 16 | B62: =Mgr_16!B10 | C62: =Mgr_16!C10 | D62: =Mgr_16!D10 | E62: =Mgr_16!E10 | F62: =Mgr_16!F10 | G62: =Mgr_16!G10 | H62: =Mgr_16!H10 | I62: =Mgr_16!I10 | ... AF62: =Mgr_16!AF10
A63: Менеджер 17 | B63: =Mgr_17!B10 | C63: =Mgr_17!C10 | D63: =Mgr_17!D10 | E63: =Mgr_17!E10 | F63: =Mgr_17!F10 | G63: =Mgr_17!G10 | H63: =Mgr_17!H10 | I63: =Mgr_17!I10 | ... AF63: =Mgr_17!AF10
A64: Менеджер 18 | B64: =Mgr_18!B10 | C64: =Mgr_18!C10 | D64: =Mgr_18!D10 | E64: =Mgr_18!E10 | F64: =Mgr_18!F10 | G64: =Mgr_18!G10 | H64: =Mgr_18!H10 | I64: =Mgr_18!I10 | ... AF64: =Mgr_18!AF10
A65: Менеджер 19 | B65: =Mgr_19!B10 | C65: =Mgr_19!C10 | D65: =Mgr_19!D10 | E65: =Mgr_19!E10 | F65: =Mgr_19!F10 | G65: =Mgr_19!G10 | H65: =Mgr_19!H10 | I65: =Mgr_19!I10 | ... AF65: =Mgr_19!AF10
A66: Менеджер 20 | B66: =Mgr_20!B10 | C66: =Mgr_20!C10 | D66: =Mgr_20!D10 | E66: =Mgr_20!E10 | F66: =Mgr_20!F10 | G66: =Mgr_20!G10 | H66: =Mgr_20!H10 | I66: =Mgr_20!I10 | ... AF66: =Mgr_20!AF10
A68: 📆 РЕЙТИНГ ПО НЕДЕЛЯМ (ВЫРУЧКА)
A69: Менеджер | B69: Неделя 1 | C69: Неделя 2 | D69: Неделя 3 | E69: Неделя 4 | F69: Неделя 5 | G69: ИТОГО за месяц
A70: Менеджер 1 | B70: =SUM(Mgr_1!B10:H10) | C70: =SUM(Mgr_1!I10:O10) | D70: =SUM(Mgr_1!P10:V10) | E70: =SUM(Mgr_1!W10:AC10) | F70: =SUM(Mgr_1!AD10:AF10) | G70: =SUM(B70:F70)
A71: Менеджер 2 | B71: =SUM(Mgr_2!B10:H10) | C71: =SUM(Mgr_2!I10:O10) | D71: =SUM(Mgr_2!P10:V10) | E71: =SUM(Mgr_2!W10:AC10) | F71: =SUM(Mgr_2!AD10:AF10) | G71: =SUM(B71:F71)
A72: Менеджер 3 | B72: =SUM(Mgr_3!B10:H10) | C72: =SUM(Mgr_3!I10:O10) | D72: =SUM(Mgr_3!P10:V10) | E72: =SUM(Mgr_3!W10:AC10) | F72: =SUM(Mgr_3!AD10:AF10) | G72: =SUM(B72:F72)
A73: Менеджер 4 | B73: =SUM(Mgr_4!B10:H10) | C73: =SUM(Mgr_4!I10:O10) | D73: =SUM(Mgr_4!P10:V10) | E73: =SUM(Mgr_4!W10:AC10) | F73: =SUM(Mgr_4!AD10:AF10) | G73: =SUM(B73:F73)
A74: Менеджер 5 | B74: =SUM(Mgr_5!B10:H10) | C74: =SUM(Mgr_5!I10:O10) | D74: =SUM(Mgr_5!P10:V10) | E74: =SUM(Mgr_5!W10:AC10) | F74: =SUM(Mgr_5!AD10:AF10) | G74: =SUM(B74:F74)
A75: Менеджер 6 | B75: =SUM(Mgr_6!B10:H10) | C75: =SUM(Mgr_6!I10:O10) | D75: =SUM(Mgr_6!P10:V10) | E75: =SUM(Mgr_6!W10:AC10) | F75: =SUM(Mgr_6!AD10:AF10) | G75: =SUM(B75:F75)
A76: Менеджер 7 | B76: =SUM(Mgr_7!B10:H10) | C76: =SUM(Mgr_7!I10:O10) | D76: =SUM(Mgr_7!P10:V10) | E76: =SUM(Mgr_7!W10:AC10) | F76: =SUM(Mgr_7!AD10:AF10) | G76: =SUM(B76:F76)
A77: Менеджер 8 | B77: =SUM(Mgr_8!B10:H10) | C77: =SUM(Mgr_8!I10:O10) | D77: =SUM(Mgr_8!P10:V10) | E77: =SUM(Mgr_8!W10:AC10) | F77: =SUM(Mgr_8!AD10:AF10) | G77: =SUM(B77:F77)
A78: Менеджер 9 | B78: =SUM(Mgr_9!B10:H10) | C78: =SUM(Mgr_9!I10:O10) | D78: =SUM(Mgr_9!P10:V10) | E78: =SUM(Mgr_9!W10:AC10) | F78: =SUM(Mgr_9!AD10:AF10) | G78: =SUM(B78:F78)
A79: Менеджер 10 | B79: =SUM(Mgr_10!B10:H10) | C79: =SUM(Mgr_10!I10:O10) | D79: =SUM(Mgr_10!P10:V10) | E79: =SUM(Mgr_10!W10:AC10) | F79: =SUM(Mgr_10!AD10:AF10) | G79: =SUM(B79:F79)
A80: Менеджер 11 | B80: =SUM(Mgr_11!B10:H10) | C80: =SUM(Mgr_11!I10:O10) | D80: =SUM(Mgr_11!P10:V10) | E80: =SUM(Mgr_11!W10:AC10) | F80: =SUM(Mgr_11!AD10:AF10) | G80: =SUM(B80:F80)
A81: Менеджер 12 | B81: =SUM(Mgr_12!B10:H10) | C81: =SUM(Mgr_12!I10:O10) | D81: =SUM(Mgr_12!P10:V10) | E81: =SUM(Mgr_12!W10:AC10) | F81: =SUM(Mgr_12!AD10:AF10) | G81: =SUM(B81:F81)
A82: Менеджер 13 | B82: =SUM(Mgr_13!B10:H10) | C82: =SUM(Mgr_13!I10:O10) | D82: =SUM(Mgr_13!P10:V10) | E82: =SUM(Mgr_13!W10:AC10) | F82: =SUM(Mgr_13!AD10:AF10) | G82: =SUM(B82:F82)
A83: Менеджер 14 | B83: =SUM(Mgr_14!B10:H10) | C83: =SUM(Mgr_14!I10:O10) | D83: =SUM(Mgr_14!P10:V10) | E83: =SUM(Mgr_14!W10:AC10) | F83: =SUM(Mgr_14!AD10:AF10) | G83: =SUM(B83:F83)
A84: Менеджер 15 | B84: =SUM(Mgr_15!B10:H10) | C84: =SUM(Mgr_15!I10:O10) | D84: =SUM(Mgr_15!P10:V10) | E84: =SUM(Mgr_15!W10:AC10) | F84: =SUM(Mgr_15!AD10:AF10) | G84: =SUM(B84:F84)
A85: Менеджер 16 | B85: =SUM(Mgr_16!B10:H10) | C85: =SUM(Mgr_16!I10:O10) | D85: =SUM(Mgr_16!P10:V10) | E85: =SUM(Mgr_16!W10:AC10) | F85: =SUM(Mgr_16!AD10:AF10) | G85: =SUM(B85:F85)
A86: Менеджер 17 | B86: =SUM(Mgr_17!B10:H10) | C86: =SUM(Mgr_17!I10:O10) | D86: =SUM(Mgr_17!P10:V10) | E86: =SUM(Mgr_17!W10:AC10) | F86: =SUM(Mgr_17!AD10:AF10) | G86: =SUM(B86:F86)
A87: Менеджер 18 | B87: =SUM(Mgr_18!B10:H10) | C87: =SUM(Mgr_18!I10:O10) | D87: =SUM(Mgr_18!P10:V10) | E87: =SUM(Mgr_18!W10:AC10) | F87: =SUM(Mgr_18!AD10:AF10) | G87: =SUM(B87:F87)
A88: Менеджер 19 | B88: =SUM(Mgr_19!B10:H10) | C88: =SUM(Mgr_19!I10:O10) | D88: =SUM(Mgr_19!P10:V10) | E88: =SUM(Mgr_19!W10:AC10) | F88: =SUM(Mgr_19!AD10:AF10) | G88: =SUM(B88:F88)
A89: Менеджер 20 | B89: =SUM(Mgr_20!B10:H10) | C89: =SUM(Mgr_20!I10:O10) | D89: =SUM(Mgr_20!P10:V10) | E89: =SUM(Mgr_20!W10:AC10) | F89: =SUM(Mgr_20!AD10:AF10) | G89: =SUM(B89:F89)
A91: 📊 РЕЙТИНГ ПО МЕСЯЦАМ ГОДА (ВЫРУЧКА)
A92: Менеджер | B92: Янв | C92: Фев | D92: Мар | E92: Апр | F92: Май | G92: Июн | H92: Июл | I92: Авг | J92: Сен | K92: Окт | L92: Ноя | M92: Дек | N92: ИТОГО год
A93: Менеджер 1 | B93: 0 | C93: =Mgr_1!AG10 | D93: 0 | E93: 0 | F93: 0 | G93: 0 | H93: 0 | I93: 0 | J93: 0 | K93: 0 | L93: 0 | M93: 0 | N93: =SUM(B93:M93)
A94: Менеджер 2 | B94: 0 | C94: =Mgr_2!AG10 | D94: 0 | E94: 0 | F94: 0 | G94: 0 | H94: 0 | I94: 0 | J94: 0 | K94: 0 | L94: 0 | M94: 0 | N94: =SUM(B94:M94)
A95: Менеджер 3 | B95: 0 | C95: =Mgr_3!AG10 | D95: 0 | E95: 0 | F95: 0 | G95: 0 | H95: 0 | I95: 0 | J95: 0 | K95: 0 | L95: 0 | M95: 0 | N95: =SUM(B95:M95)
A96: Менеджер 4 | B96: 0 | C96: =Mgr_4!AG10 | D96: 0 | E96: 0 | F96: 0 | G96: 0 | H96: 0 | I96: 0 | J96: 0 | K96: 0 | L96: 0 | M96: 0 | N96: =SUM(B96:M96)
A97: Менеджер 5 | B97: 0 | C97: =Mgr_5!AG10 | D97: 0 | E97: 0 | F97: 0 | G97: 0 | H97: 0 | I97: 0 | J97: 0 | K97: 0 | L97: 0 | M97: 0 | N97: =SUM(B97:M97)
A98: Менеджер 6 | B98: 0 | C98: =Mgr_6!AG10 | D98: 0 | E98: 0 | F98: 0 | G98: 0 | H98: 0 | I98: 0 | J98: 0 | K98: 0 | L98: 0 | M98: 0 | N98: =SUM(B98:M98)
A99: Менеджер 7 | B99: 0 | C99: =Mgr_7!AG10 | D99: 0 | E99: 0 | F99: 0 | G99: 0 | H99: 0 | I99: 0 | J99: 0 | K99: 0 | L99: 0 | M99: 0 | N99: =SUM(B99:M99)
A100: Менеджер 8 | B100: 0 | C100: =Mgr_8!AG10 | D100: 0 | E100: 0 | F100: 0 | G100: 0 | H100: 0 | I100: 0 | J100: 0 | K100: 0 | L100: 0 | M100: 0 | N100: =SUM(B100:M100)
A101: Менеджер 9 | B101: 0 | C101: =Mgr_9!AG10 | D101: 0 | E101: 0 | F101: 0 | G101: 0 | H101: 0 | I101: 0 | J101: 0 | K101: 0 | L101: 0 | M101: 0 | N101: =SUM(B101:M101)
A102: Менеджер 10 | B102: 0 | C102: =Mgr_10!AG10 | D102: 0 | E102: 0 | F102: 0 | G102: 0 | H102: 0 | I102: 0 | J102: 0 | K102: 0 | L102: 0 | M102: 0 | N102: =SUM(B102:M102)
A103: Менеджер 11 | B103: 0 | C103: =Mgr_11!AG10 | D103: 0 | E103: 0 | F103: 0 | G103: 0 | H103: 0 | I103: 0 | J103: 0 | K103: 0 | L103: 0 | M103: 0 | N103: =SUM(B103:M103)
A104: Менеджер 12 | B104: 0 | C104: =Mgr_12!AG10 | D104: 0 | E104: 0 | F104: 0 | G104: 0 | H104: 0 | I104: 0 | J104: 0 | K104: 0 | L104: 0 | M104: 0 | N104: =SUM(B104:M104)
A105: Менеджер 13 | B105: 0 | C105: =Mgr_13!AG10 | D105: 0 | E105: 0 | F105: 0 | G105: 0 | H105: 0 | I105: 0 | J105: 0 | K105: 0 | L105: 0 | M105: 0 | N105: =SUM(B105:M105)
A106: Менеджер 14 | B106: 0 | C106: =Mgr_14!AG10 | D106: 0 | E106: 0 | F106: 0 | G106: 0 | H106: 0 | I106: 0 | J106: 0 | K106: 0 | L106: 0 | M106: 0 | N106: =SUM(B106:M106)
A107: Менеджер 15 | B107: 0 | C107: =Mgr_15!AG10 | D107: 0 | E107: 0 | F107: 0 | G107: 0 | H107: 0 | I107: 0 | J107: 0 | K107: 0 | L107: 0 | M107: 0 | N107: =SUM(B107:M107)
A108: Менеджер 16 | B108: 0 | C108: =Mgr_16!AG10 | D108: 0 | E108: 0 | F108: 0 | G108: 0 | H108: 0 | I108: 0 | J108: 0 | K108: 0 | L108: 0 | M108: 0 | N108: =SUM(B108:M108)
A109: Менеджер 17 | B109: 0 | C109: =Mgr_17!AG10 | D109: 0 | E109: 0 | F109: 0 | G109: 0 | H109: 0 | I109: 0 | J109: 0 | K109: 0 | L109: 0 | M109: 0 | N109: =SUM(B109:M109)
A110: Менеджер 18 | B110: 0 | C110: =Mgr_18!AG10 | D110: 0 | E110: 0 | F110: 0 | G110: 0 | H110: 0 | I110: 0 | J110: 0 | K110: 0 | L110: 0 | M110: 0 | N110: =SUM(B110:M110)
A111: Менеджер 19 | B111: 0 | C111: =Mgr_19!AG10 | D111: 0 | E111: 0 | F111: 0 | G111: 0 | H111: 0 | I111: 0 | J111: 0 | K111: 0 | L111: 0 | M111: 0 | N111: =SUM(B111:M111)
A112: Менеджер 20 | B112: 0 | C112: =Mgr_20!AG10 | D112: 0 | E112: 0 | F112: 0 | G112: 0 | H112: 0 | I112: 0 | J112: 0 | K112: 0 | L112: 0 | M112: 0 | N112: =SUM(B112:M112)
A115: 📊 CRM Dashboard v3.0 | Полный функционал: Остаток, Комментарии, Статистика | Все формулы работают ✓
A120: 📊 CRM Dashboard v4.0 | 💡 Светло-синий фон = формулы | Ежедневный отчет - ручной ввод | Статус оплаты: 🟢 Полностью = зеленый, 🟡 Не полный = желтый | ✅ 5119 формул работают корректно

Sheet Mgr_1
A1: 📈 ЕЖЕДНЕВНЫЙ ОТЧЕТ - МЕНЕДЖЕР 1
A2: ПОКАЗАТЕЛИ ЭФФЕКТИВНОСТИ ПО ДНЯМ МЕСЯЦА
A3: МЕТРИКА / ДАТА | B3: 01 | C3: 02 | D3: 03 | E3: 04 | F3: 05 | G3: 06 | H3: 07 | I3: 08 | J3: 09 | K3: 10 | L3: 11 | M3: 12 | N3: 13 | O3: 14 | P3: 15 | Q3: 16 | R3: 17 | S3: 18 | T3: 19 | U3: 20 | V3: 21 | W3: 22 | X3: 23 | Y3: 24 | Z3: 25 | AA3: 26 | AB3: 27 | AC3: 28 | AD3: 29 | AE3: 30 | AF3: 31 | AG3: ИТОГО
A4: Лиды | N4: 10 | O4: 10 | AG4: =SUM(B4:AF4)
A5: Обработка | N5: 1 | AG5: =SUM(B5:AF5)
A6: Не дозвон | N6: 1 | O6: 10 | AG6: =SUM(B6:AF6)
A7: Ожидание | O7: 10 | AG7: =SUM(B7:AF7)
A8: Отказ | N8: 3 | AG8: =SUM(B8:AF8)
A9: Продажа | N9: 1 | O9: 4 | AG9: =SUM(B9:AF9)
A10: Выручка (сом) | N10: 40000 | O10: 10000 | AG10: =SUM(B10:AF10)
A11: Конверсия % | AG11: =IF(AG4=0,0,AG9/AG4*100)
A12: Остаток (сом) | AG12: =SUM(B12:AF12)
A14: 💡 ИНСТРУКЦИЯ: Заполняйте ежедневный отчет вручную (строки 4-12). В таблице клиентов выбирайте "Статус оплаты" из списка. Остаток рассчитывается автоматически.
A15: 📋 РЕЕСТР КЛИЕНТОВ - МЕНЕДЖЕР 1
A16: № | B16: ФИ Клиента | C16: Регион | D16: Телефон | E16: Цена курса (сом) | F16: Статус оплаты | G16: Дата след. оплаты | H16: Остаток (сом) | I16: Комментарий
A38: РЕЕСТР ЛИДОВ - МЕНЕДЖЕР 1
A40: № | J40: Дата платежа | K40: Комментарий
A41: 1
A42: 2
A43: 3
A44: 4
A45: 5

Sheet Mgr_2
A1: 📈 ЕЖЕДНЕВНЫЙ ОТЧЕТ - МЕНЕДЖЕР 2
A2: ПОКАЗАТЕЛИ ЭФФЕКТИВНОСТИ ПО ДНЯМ МЕСЯЦА
A3: МЕТРИКА / ДАТА | B3: 01 | C3: 02 | D3: 03 | E3: 04 | F3: 05 | G3: 06 | H3: 07 | I3: 08 | J3: 09 | K3: 10 | L3: 11 | M3: 12 | N3: 13 | O3: 14 | P3: 15 | Q3: 16 | R3: 17 | S3: 18 | T3: 19 | U3: 20 | V3: 21 | W3: 22 | X3: 23 | Y3: 24 | Z3: 25 | AA3: 26 | AB3: 27 | AC3: 28 | AD3: 29 | AE3: 30 | AF3: 31 | AG3: ИТОГО
A4: Лиды | AG4: =SUM(B4:AF4)
A5: Обработка | AG5: =SUM(B5:AF5)
A6: Не дозвон | AG6: =SUM(B6:AF6)
A7: Ожидание | AG7: =SUM(B7:AF7)
A8: Отказ | AG8: =SUM(B8:AF8)
A9: Продажа | AG9: =SUM(B9:AF9)
A10: Выручка (сом) | AG10: =SUM(B10:AF10)
A11: Конверсия % | AG11: =IF(AG4=0,0,AG9/AG4*100)
A12: Остаток (сом) | AG12: =SUM(B12:AF12)
A15: 📋 РЕЕСТР КЛИЕНТОВ - МЕНЕДЖЕР 2
A16: № | B16: ФИ Клиента | C16: Регион | D16: Телефон | E16: Цена курса (сом) | F16: Статус оплаты | G16: Дата след. оплаты | H16: Остаток (сом) | I16: Комментарий
A38: РЕЕСТР ЛИДОВ - МЕНЕДЖЕР 2
A40: № | J40: Дата платежа | K40: Комментарий
A41: 1
A42: 2
A43: 3
A44: 4
A45: 5

Sheet Mgr_3
A1: 📈 ЕЖЕДНЕВНЫЙ ОТЧЕТ - МЕНЕДЖЕР 3
A2: ПОКАЗАТЕЛИ ЭФФЕКТИВНОСТИ ПО ДНЯМ МЕСЯЦА
A3: МЕТРИКА / ДАТА | B3: 01 | C3: 02 | D3: 03 | E3: 04 | F3: 05 | G3: 06 | H3: 07 | I3: 08 | J3: 09 | K3: 10 | L3: 11 | M3: 12 | N3: 13 | O3: 14 | P3: 15 | Q3: 16 | R3: 17 | S3: 18 | T3: 19 | U3: 20 | V3: 21 | W3: 22 | X3: 23 | Y3: 24 | Z3: 25 | AA3: 26 | AB3: 27 | AC3: 28 | AD3: 29 | AE3: 30 | AF3: 31 | AG3: ИТОГО
A4: Лиды | AG4: =SUM(B4:AF4)
A5: Обработка | AG5: =SUM(B5:AF5)
A6: Не дозвон | AG6: =SUM(B6:AF6)
A7: Ожидание | AG7: =SUM(B7:AF7)
A8: Отказ | AG8: =SUM(B8:AF8)
A9: Продажа | AG9: =SUM(B9:AF9)
A10: Выручка (сом) | AG10: =SUM(B10:AF10)
A11: Конверсия % | AG11: =IF(AG4=0,0,AG9/AG4*100)
A12: Остаток (сом) | AG12: =SUM(B12:AF12)
A15: 📋 РЕЕСТР КЛИЕНТОВ - МЕНЕДЖЕР 3
A16: № | B16: ФИ Клиента | C16: Регион | D16: Телефон | E16: Цена курса (сом) | F16: Статус оплаты | G16: Дата след. оплаты | H16: Остаток (сом) | I16: Комментарий
A38: РЕЕСТР ЛИДОВ - МЕНЕДЖЕР 3
A40: № | J40: Дата платежа | K40: Комментарий
A41: 1
A42: 2
A43: 3
A44: 4
A45: 5

Sheet Mgr_4
A1: 📈 ЕЖЕДНЕВНЫЙ ОТЧЕТ - МЕНЕДЖЕР 4
A2: ПОКАЗАТЕЛИ ЭФФЕКТИВНОСТИ ПО ДНЯМ МЕСЯЦА
A3: МЕТРИКА / ДАТА | B3: 01 | C3: 02 | D3: 03 | E3: 04 | F3: 05 | G3: 06 | H3: 07 | I3: 08 | J3: 09 | K3: 10 | L3: 11 | M3: 12 | N3: 13 | O3: 14 | P3: 15 | Q3: 16 | R3: 17 | S3: 18 | T3: 19 | U3: 20 | V3: 21 | W3: 22 | X3: 23 | Y3: 24 | Z3: 25 | AA3: 26 | AB3: 27 | AC3: 28 | AD3: 29 | AE3: 30 | AF3: 31 | AG3: ИТОГО
A4: Лиды | AG4: =SUM(B4:AF4)
A5: Обработка | AG5: =SUM(B5:AF5)
A6: Не дозвон | AG6: =SUM(B6:AF6)
A7: Ожидание | AG7: =SUM(B7:AF7)
A8: Отказ | AG8: =SUM(B8:AF8)
A9: Продажа | AG9: =SUM(B9:AF9)
A10: Выручка (сом) | AG10: =SUM(B10:AF10)
A11: Конверсия % | AG11: =IF(AG4=0,0,AG9/AG4*100)
A12: Остаток (сом) | AG12: =SUM(B12:AF12)
A15: 📋 РЕЕСТР КЛИЕНТОВ - МЕНЕДЖЕР 4
A16: № | B16: ФИ Клиента | C16: Регион | D16: Телефон | E16: Цена курса (сом) | F16: Статус оплаты | G16: Дата след. оплаты | H16: Остаток (сом) | I16: Комментарий
A38: РЕЕСТР ЛИДОВ - МЕНЕДЖЕР 4
A40: № | J40: Дата платежа | K40: Комментарий
A41: 1
A42: 2
A43: 3
A44: 4
A45: 5

Sheet Mgr_5
A1: 📈 ЕЖЕДНЕВНЫЙ ОТЧЕТ - МЕНЕДЖЕР 5
A2: ПОКАЗАТЕЛИ ЭФФЕКТИВНОСТИ ПО ДНЯМ МЕСЯЦА
A3: МЕТРИКА / ДАТА | B3: 01 | C3: 02 | D3: 03 | E3: 04 | F3: 05 | G3: 06 | H3: 07 | I3: 08 | J3: 09 | K3: 10 | L3: 11 | M3: 12 | N3: 13 | O3: 14 | P3: 15 | Q3: 16 | R3: 17 | S3: 18 | T3: 19 | U3: 20 | V3: 21 | W3: 22 | X3: 23 | Y3: 24 | Z3: 25 | AA3: 26 | AB3: 27 | AC3: 28 | AD3: 29 | AE3: 30 | AF3: 31 | AG3: ИТОГО
A4: Лиды | AG4: =SUM(B4:AF4)
A5: Обработка | AG5: =SUM(B5:AF5)
A6: Не дозвон | AG6: =SUM(B6:AF6)
A7: Ожидание | AG7: =SUM(B7:AF7)
A8: Отказ | AG8: =SUM(B8:AF8)
A9: Продажа | AG9: =SUM(B9:AF9)
A10: Выручка (сом) | AG10: =SUM(B10:AF10)
A11: Конверсия % | AG11: =IF(AG4=0,0,AG9/AG4*100)
A12: Остаток (сом) | AG12: =SUM(B12:AF12)
A15: 📋 РЕЕСТР КЛИЕНТОВ - МЕНЕДЖЕР 5
A16: № | B16: ФИ Клиента | C16: Регион | D16: Телефон | E16: Цена курса (сом) | F16: Статус оплаты | G16: Дата след. оплаты | H16: Остаток (сом) | I16: Комментарий
A38: РЕЕСТР ЛИДОВ - МЕНЕДЖЕР 5
A40: № | J40: Дата платежа | K40: Комментарий
A41: 1
A42: 2
A43: 3
A44: 4
A45: 5

Sheet Mgr_6
A1: 📈 ЕЖЕДНЕВНЫЙ ОТЧЕТ - МЕНЕДЖЕР 6
A2: ПОКАЗАТЕЛИ ЭФФЕКТИВНОСТИ ПО ДНЯМ МЕСЯЦА
A3: МЕТРИКА / ДАТА | B3: 01 | C3: 02 | D3: 03 | E3: 04 | F3: 05 | G3: 06 | H3: 07 | I3: 08 | J3: 09 | K3: 10 | L3: 11 | M3: 12 | N3: 13 | O3: 14 | P3: 15 | Q3: 16 | R3: 17 | S3: 18 | T3: 19 | U3: 20 | V3: 21 | W3: 22 | X3: 23 | Y3: 24 | Z3: 25 | AA3: 26 | AB3: 27 | AC3: 28 | AD3: 29 | AE3: 30 | AF3: 31 | AG3: ИТОГО
A4: Лиды | AG4: =SUM(B4:AF4)
A5: Обработка | AG5: =SUM(B5:AF5)
A6: Не дозвон | AG6: =SUM(B6:AF6)
A7: Ожидание | AG7: =SUM(B7:AF7)
A8: Отказ | AG8: =SUM(B8:AF8)
A9: Продажа | AG9: =SUM(B9:AF9)
A10: Выручка (сом) | AG10: =SUM(B10:AF10)
A11: Конверсия % | AG11: =IF(AG4=0,0,AG9/AG4*100)
A12: Остаток (сом) | AG12: =SUM(B12:AF12)
A15: 📋 РЕЕСТР КЛИЕНТОВ - МЕНЕДЖЕР 6
A16: № | B16: ФИ Клиента | C16: Регион | D16: Телефон | E16: Цена курса (сом) | F16: Статус оплаты | G16: Дата след. оплаты | H16: Остаток (сом) | I16: Комментарий
A38: РЕЕСТР ЛИДОВ - МЕНЕДЖЕР 6
A40: № | J40: Дата платежа | K40: Комментарий
A41: 1
A42: 2
A43: 3
A44: 4
A45: 5

Sheet Mgr_7
A1: 📈 ЕЖЕДНЕВНЫЙ ОТЧЕТ - МЕНЕДЖЕР 7
A2: ПОКАЗАТЕЛИ ЭФФЕКТИВНОСТИ ПО ДНЯМ МЕСЯЦА
A3: МЕТРИКА / ДАТА | B3: 01 | C3: 02 | D3: 03 | E3: 04 | F3: 05 | G3: 06 | H3: 07 | I3: 08 | J3: 09 | K3: 10 | L3: 11 | M3: 12 | N3: 13 | O3: 14 | P3: 15 | Q3: 16 | R3: 17 | S3: 18 | T3: 19 | U3: 20 | V3: 21 | W3: 22 | X3: 23 | Y3: 24 | Z3: 25 | AA3: 26 | AB3: 27 | AC3: 28 | AD3: 29 | AE3: 30 | AF3: 31 | AG3: ИТОГО
A4: Лиды | AG4: =SUM(B4:AF4)
A5: Обработка | AG5: =SUM(B5:AF5)
A6: Не дозвон | AG6: =SUM(B6:AF6)
A7: Ожидание | AG7: =SUM(B7:AF7)
A8: Отказ | AG8: =SUM(B8:AF8)
A9: Продажа | AG9: =SUM(B9:AF9)
A10: Выручка (сом) | AG10: =SUM(B10:AF10)
A11: Конверсия % | AG11: =IF(AG4=0,0,AG9/AG4*100)
A12: Остаток (сом) | AG12: =SUM(B12:AF12)
A15: 📋 РЕЕСТР КЛИЕНТОВ - МЕНЕДЖЕР 7
A16: № | B16: ФИ Клиента | C16: Регион | D16: Телефон | E16: Цена курса (сом) | F16: Статус оплаты | G16: Дата след. оплаты | H16: Остаток (сом) | I16: Комментарий
A38: РЕЕСТР ЛИДОВ - МЕНЕДЖЕР 7
A40: № | J40: Дата платежа | K40: Комментарий
A41: 1
A42: 2
A43: 3
A44: 4
A45: 5

Sheet Mgr_8
A1: 📈 ЕЖЕДНЕВНЫЙ ОТЧЕТ - МЕНЕДЖЕР 8
A2: ПОКАЗАТЕЛИ ЭФФЕКТИВНОСТИ ПО ДНЯМ МЕСЯЦА
A3: МЕТРИКА / ДАТА | B3: 01 | C3: 02 | D3: 03 | E3: 04 | F3: 05 | G3: 06 | H3: 07 | I3: 08 | J3: 09 | K3: 10 | L3: 11 | M3: 12 | N3: 13 | O3: 14 | P3: 15 | Q3: 16 | R3: 17 | S3: 18 | T3: 19 | U3: 20 | V3: 21 | W3: 22 | X3: 23 | Y3: 24 | Z3: 25 | AA3: 26 | AB3: 27 | AC3: 28 | AD3: 29 | AE3: 30 | AF3: 31 | AG3: ИТОГО
A4: Лиды | AG4: =SUM(B4:AF4)
A5: Обработка | AG5: =SUM(B5:AF5)
A6: Не дозвон | AG6: =SUM(B6:AF6)
A7: Ожидание | AG7: =SUM(B7:AF7)
A8: Отказ | AG8: =SUM(B8:AF8)
A9: Продажа | AG9: =SUM(B9:AF9)
A10: Выручка (сом) | AG10: =SUM(B10:AF10)
A11: Конверсия % | AG11: =IF(AG4=0,0,AG9/AG4*100)
A12: Остаток (сом) | AG12: =SUM(B12:AF12)
A15: 📋 РЕЕСТР КЛИЕНТОВ - МЕНЕДЖЕР 8
A16: № | B16: ФИ Клиента | C16: Регион | D16: Телефон | E16: Цена курса (сом) | F16: Статус оплаты | G16: Дата след. оплаты | H16: Остаток (сом) | I16: Комментарий
A38: РЕЕСТР ЛИДОВ - МЕНЕДЖЕР 8
A40: № | J40: Дата платежа | K40: Комментарий
A41: 1
A42: 2
A43: 3
A44: 4
A45: 5

Sheet Mgr_9
A1: 📈 ЕЖЕДНЕВНЫЙ ОТЧЕТ - МЕНЕДЖЕР 9
A2: ПОКАЗАТЕЛИ ЭФФЕКТИВНОСТИ ПО ДНЯМ МЕСЯЦА
A3: МЕТРИКА / ДАТА | B3: 01 | C3: 02 | D3: 03 | E3: 04 | F3: 05 | G3: 06 | H3: 07 | I3: 08 | J3: 09 | K3: 10 | L3: 11 | M3: 12 | N3: 13 | O3: 14 | P3: 15 | Q3: 16 | R3: 17 | S3: 18 | T3: 19 | U3: 20 | V3: 21 | W3: 22 | X3: 23 | Y3: 24 | Z3: 25 | AA3: 26 | AB3: 27 | AC3: 28 | AD3: 29 | AE3: 30 | AF3: 31 | AG3: ИТОГО
A4: Лиды | AG4: =SUM(B4:AF4)
A5: Обработка | AG5: =SUM(B5:AF5)
A6: Не дозвон | AG6: =SUM(B6:AF6)
A7: Ожидание | AG7: =SUM(B7:AF7)
A8: Отказ | AG8: =SUM(B8:AF8)
A9: Продажа | AG9: =SUM(B9:AF9)
A10: Выручка (сом) | AG10: =SUM(B10:AF10)
A11: Конверсия % | AG11: =IF(AG4=0,0,AG9/AG4*100)
A12: Остаток (сом) | AG12: =SUM(B12:AF12)
A15: 📋 РЕЕСТР КЛИЕНТОВ - МЕНЕДЖЕР 9
A16: № | B16: ФИ Клиента | C16: Регион | D16: Телефон | E16: Цена курса (сом) | F16: Статус оплаты | G16: Дата след. оплаты | H16: Остаток (сом) | I16: Комментарий
A38: РЕЕСТР ЛИДОВ - МЕНЕДЖЕР 9
A40: № | J40: Дата платежа | K40: Комментарий
A41: 1
A42: 2
A43: 3
A44: 4
A45: 5

Sheet Mgr_10
A1: 📈 ЕЖЕДНЕВНЫЙ ОТЧЕТ - МЕНЕДЖЕР 10
A2: ПОКАЗАТЕЛИ ЭФФЕКТИВНОСТИ ПО ДНЯМ МЕСЯЦА
A3: МЕТРИКА / ДАТА | B3: 01 | C3: 02 | D3: 03 | E3: 04 | F3: 05 | G3: 06 | H3: 07 | I3: 08 | J3: 09 | K3: 10 | L3: 11 | M3: 12 | N3: 13 | O3: 14 | P3: 15 | Q3: 16 | R3: 17 | S3: 18 | T3: 19 | U3: 20 | V3: 21 | W3: 22 | X3: 23 | Y3: 24 | Z3: 25 | AA3: 26 | AB3: 27 | AC3: 28 | AD3: 29 | AE3: 30 | AF3: 31 | AG3: ИТОГО
A4: Лиды | AG4: =SUM(B4:AF4)
A5: Обработка | AG5: =SUM(B5:AF5)
A6: Не дозвон | AG6: =SUM(B6:AF6)
A7: Ожидание | AG7: =SUM(B7:AF7)
A8: Отказ | AG8: =SUM(B8:AF8)
A9: Продажа | AG9: =SUM(B9:AF9)
A10: Выручка (сом) | AG10: =SUM(B10:AF10)
A11: Конверсия % | AG11: =IF(AG4=0,0,AG9/AG4*100)
A12: Остаток (сом) | AG12: =SUM(B12:AF12)
A15: 📋 РЕЕСТР КЛИЕНТОВ - МЕНЕДЖЕР 10
A16: № | B16: ФИ Клиента | C16: Регион | D16: Телефон | E16: Цена курса (сом) | F16: Статус оплаты | G16: Дата след. оплаты | H16: Остаток (сом) | I16: Комментарий
A38: РЕЕСТР ЛИДОВ - МЕНЕДЖЕР 10
A40: № | J40: Дата платежа | K40: Комментарий
A41: 1
A42: 2
A43: 3
A44: 4
A45: 5

Sheet Mgr_11
A1: 📈 ЕЖЕДНЕВНЫЙ ОТЧЕТ - МЕНЕДЖЕР 11
A2: ПОКАЗАТЕЛИ ЭФФЕКТИВНОСТИ ПО ДНЯМ МЕСЯЦА
A3: МЕТРИКА / ДАТА | B3: 01 | C3: 02 | D3: 03 | E3: 04 | F3: 05 | G3: 06 | H3: 07 | I3: 08 | J3: 09 | K3: 10 | L3: 11 | M3: 12 | N3: 13 | O3: 14 | P3: 15 | Q3: 16 | R3: 17 | S3: 18 | T3: 19 | U3: 20 | V3: 21 | W3: 22 | X3: 23 | Y3: 24 | Z3: 25 | AA3: 26 | AB3: 27 | AC3: 28 | AD3: 29 | AE3: 30 | AF3: 31 | AG3: ИТОГО
A4: Лиды | AG4: =SUM(B4:AF4)
A5: Обработка | AG5: =SUM(B5:AF5)
A6: Не дозвон | AG6: =SUM(B6:AF6)
A7: Ожидание | AG7: =SUM(B7:AF7)
A8: Отказ | AG8: =SUM(B8:AF8)
A9: Продажа | AG9: =SUM(B9:AF9)
A10: Выручка (сом) | AG10: =SUM(B10:AF10)
A11: Конверсия % | AG11: =IF(AG4=0,0,AG9/AG4*100)
A12: Остаток (сом) | AG12: =SUM(B12:AF12)
A15: 📋 РЕЕСТР КЛИЕНТОВ - МЕНЕДЖЕР 11
A16: № | B16: ФИ Клиента | C16: Регион | D16: Телефон | E16: Цена курса (сом) | F16: Статус оплаты | G16: Дата след. оплаты | H16: Остаток (сом) | I16: Комментарий
A38: РЕЕСТР ЛИДОВ - МЕНЕДЖЕР 11
A40: № | J40: Дата платежа | K40: Комментарий
A41: 1
A42: 2
A43: 3
A44: 4
A45: 5

Sheet Mgr_12
A1: 📈 ЕЖЕДНЕВНЫЙ ОТЧЕТ - МЕНЕДЖЕР 12
A2: ПОКАЗАТЕЛИ ЭФФЕКТИВНОСТИ ПО ДНЯМ МЕСЯЦА
A3: МЕТРИКА / ДАТА | B3: 01 | C3: 02 | D3: 03 | E3: 04 | F3: 05 | G3: 06 | H3: 07 | I3: 08 | J3: 09 | K3: 10 | L3: 11 | M3: 12 | N3: 13 | O3: 14 | P3: 15 | Q3: 16 | R3: 17 | S3: 18 | T3: 19 | U3: 20 | V3: 21 | W3: 22 | X3: 23 | Y3: 24 | Z3: 25 | AA3: 26 | AB3: 27 | AC3: 28 | AD3: 29 | AE3: 30 | AF3: 31 | AG3: ИТОГО
A4: Лиды | AG4: =SUM(B4:AF4)
A5: Обработка | AG5: =SUM(B5:AF5)
A6: Не дозвон | AG6: =SUM(B6:AF6)
A7: Ожидание | AG7: =SUM(B7:AF7)
A8: Отказ | AG8: =SUM(B8:AF8)
A9: Продажа | AG9: =SUM(B9:AF9)
A10: Выручка (сом) | AG10: =SUM(B10:AF10)
A11: Конверсия % | AG11: =IF(AG4=0,0,AG9/AG4*100)
A12: Остаток (сом) | AG12: =SUM(B12:AF12)
A15: 📋 РЕЕСТР КЛИЕНТОВ - МЕНЕДЖЕР 12
A16: № | B16: ФИ Клиента | C16: Регион | D16: Телефон | E16: Цена курса (сом) | F16: Статус оплаты | G16: Дата след. оплаты | H16: Остаток (сом) | I16: Комментарий
A38: РЕЕСТР ЛИДОВ - МЕНЕДЖЕР 12
A40: № | J40: Дата платежа | K40: Комментарий
A41: 1
A42: 2
A43: 3
A44: 4
A45: 5

Sheet Mgr_13
A1: 📈 ЕЖЕДНЕВНЫЙ ОТЧЕТ - МЕНЕДЖЕР 13
A2: ПОКАЗАТЕЛИ ЭФФЕКТИВНОСТИ ПО ДНЯМ МЕСЯЦА
A3: МЕТРИКА / ДАТА | B3: 01 | C3: 02 | D3: 03 | E3: 04 | F3: 05 | G3: 06 | H3: 07 | I3: 08 | J3: 09 | K3: 10 | L3: 11 | M3: 12 | N3: 13 | O3: 14 | P3: 15 | Q3: 16 | R3: 17 | S3: 18 | T3: 19 | U3: 20 | V3: 21 | W3: 22 | X3: 23 | Y3: 24 | Z3: 25 | AA3: 26 | AB3: 27 | AC3: 28 | AD3: 29 | AE3: 30 | AF3: 31 | AG3: ИТОГО
A4: Лиды | AG4: =SUM(B4:AF4)
A5: Обработка | AG5: =SUM(B5:AF5)
A6: Не дозвон | AG6: =SUM(B6:AF6)
A7: Ожидание | AG7: =SUM(B7:AF7)
A8: Отказ | AG8: =SUM(B8:AF8)
A9: Продажа | AG9: =SUM(B9:AF9)
A10: Выручка (сом) | AG10: =SUM(B10:AF10)
A11: Конверсия % | AG11: =IF(AG4=0,0,AG9/AG4*100)
A12: Остаток (сом) | AG12: =SUM(B12:AF12)
A15: 📋 РЕЕСТР КЛИЕНТОВ - МЕНЕДЖЕР 13
A16: № | B16: ФИ Клиента | C16: Регион | D16: Телефон | E16: Цена курса (сом) | F16: Статус оплаты | G16: Дата след. оплаты | H16: Остаток (сом) | I16: Комментарий
A38: РЕЕСТР ЛИДОВ - МЕНЕДЖЕР 13
A40: № | J40: Дата платежа | K40: Комментарий
A41: 1
A42: 2
A43: 3
A44: 4
A45: 5

Sheet Mgr_14
A1: 📈 ЕЖЕДНЕВНЫЙ ОТЧЕТ - МЕНЕДЖЕР 14
A2: ПОКАЗАТЕЛИ ЭФФЕКТИВНОСТИ ПО ДНЯМ МЕСЯЦА
A3: МЕТРИКА / ДАТА | B3: 01 | C3: 02 | D3: 03 | E3: 04 | F3: 05 | G3: 06 | H3: 07 | I3: 08 | J3: 09 | K3: 10 | L3: 11 | M3: 12 | N3: 13 | O3: 14 | P3: 15 | Q3: 16 | R3: 17 | S3: 18 | T3: 19 | U3: 20 | V3: 21 | W3: 22 | X3: 23 | Y3: 24 | Z3: 25 | AA3: 26 | AB3: 27 | AC3: 28 | AD3: 29 | AE3: 30 | AF3: 31 | AG3: ИТОГО
A4: Лиды | AG4: =SUM(B4:AF4)
A5: Обработка | AG5: =SUM(B5:AF5)
A6: Не дозвон | AG6: =SUM(B6:AF6)
A7: Ожидание | AG7: =SUM(B7:AF7)
A8: Отказ | AG8: =SUM(B8:AF8)
A9: Продажа | AG9: =SUM(B9:AF9)
A10: Выручка (сом) | AG10: =SUM(B10:AF10)
A11: Конверсия % | AG11: =IF(AG4=0,0,AG9/AG4*100)
A12: Остаток (сом) | AG12: =SUM(B12:AF12)
A15: 📋 РЕЕСТР КЛИЕНТОВ - МЕНЕДЖЕР 14
A16: № | B16: ФИ Клиента | C16: Регион | D16: Телефон | E16: Цена курса (сом) | F16: Статус оплаты | G16: Дата след. оплаты | H16: Остаток (сом) | I16: Комментарий
A38: РЕЕСТР ЛИДОВ - МЕНЕДЖЕР 14
A40: № | J40: Дата платежа | K40: Комментарий
A41: 1
A42: 2
A43: 3
A44: 4
A45: 5

Sheet Mgr_15
A1: 📈 ЕЖЕДНЕВНЫЙ ОТЧЕТ - МЕНЕДЖЕР 15
A2: ПОКАЗАТЕЛИ ЭФФЕКТИВНОСТИ ПО ДНЯМ МЕСЯЦА
A3: МЕТРИКА / ДАТА | B3: 01 | C3: 02 | D3: 03 | E3: 04 | F3: 05 | G3: 06 | H3: 07 | I3: 08 | J3: 09 | K3: 10 | L3: 11 | M3: 12 | N3: 13 | O3: 14 | P3: 15 | Q3: 16 | R3: 17 | S3: 18 | T3: 19 | U3: 20 | V3: 21 | W3: 22 | X3: 23 | Y3: 24 | Z3: 25 | AA3: 26 | AB3: 27 | AC3: 28 | AD3: 29 | AE3: 30 | AF3: 31 | AG3: ИТОГО
A4: Лиды | AG4: =SUM(B4:AF4)
A5: Обработка | AG5: =SUM(B5:AF5)
A6: Не дозвон | AG6: =SUM(B6:AF6)
A7: Ожидание | AG7: =SUM(B7:AF7)
A8: Отказ | AG8: =SUM(B8:AF8)
A9: Продажа | AG9: =SUM(B9:AF9)
A10: Выручка (сом) | AG10: =SUM(B10:AF10)
A11: Конверсия % | AG11: =IF(AG4=0,0,AG9/AG4*100)
A12: Остаток (сом) | AG12: =SUM(B12:AF12)
A15: 📋 РЕЕСТР КЛИЕНТОВ - МЕНЕДЖЕР 15
A16: № | B16: ФИ Клиента | C16: Регион | D16: Телефон | E16: Цена курса (сом) | F16: Статус оплаты | G16: Дата след. оплаты | H16: Остаток (сом) | I16: Комментарий
A38: РЕЕСТР ЛИДОВ - МЕНЕДЖЕР 15
A40: № | J40: Дата платежа | K40: Комментарий
A41: 1
A42: 2
A43: 3
A44: 4
A45: 5

Sheet Mgr_16
A1: 📈 ЕЖЕДНЕВНЫЙ ОТЧЕТ - МЕНЕДЖЕР 16
A2: ПОКАЗАТЕЛИ ЭФФЕКТИВНОСТИ ПО ДНЯМ МЕСЯЦА
A3: МЕТРИКА / ДАТА | B3: 01 | C3: 02 | D3: 03 | E3: 04 | F3: 05 | G3: 06 | H3: 07 | I3: 08 | J3: 09 | K3: 10 | L3: 11 | M3: 12 | N3: 13 | O3: 14 | P3: 15 | Q3: 16 | R3: 17 | S3: 18 | T3: 19 | U3: 20 | V3: 21 | W3: 22 | X3: 23 | Y3: 24 | Z3: 25 | AA3: 26 | AB3: 27 | AC3: 28 | AD3: 29 | AE3: 30 | AF3: 31 | AG3: ИТОГО
A4: Лиды | AG4: =SUM(B4:AF4)
A5: Обработка | AG5: =SUM(B5:AF5)
A6: Не дозвон | AG6: =SUM(B6:AF6)
A7: Ожидание | AG7: =SUM(B7:AF7)
A8: Отказ | AG8: =SUM(B8:AF8)
A9: Продажа | AG9: =SUM(B9:AF9)
A10: Выручка (сом) | AG10: =SUM(B10:AF10)
A11: Конверсия % | AG11: =IF(AG4=0,0,AG9/AG4*100)
A12: Остаток (сом) | AG12: =SUM(B12:AF12)
A15: 📋 РЕЕСТР КЛИЕНТОВ - МЕНЕДЖЕР 16
A16: № | B16: ФИ Клиента | C16: Регион | D16: Телефон | E16: Цена курса (сом) | F16: Статус оплаты | G16: Дата след. оплаты | H16: Остаток (сом) | I16: Комментарий
A38: РЕЕСТР ЛИДОВ - МЕНЕДЖЕР 16
A40: № | J40: Дата платежа | K40: Комментарий
A41: 1
A42: 2
A43: 3
A44: 4
A45: 5

Sheet Mgr_17
A1: 📈 ЕЖЕДНЕВНЫЙ ОТЧЕТ - МЕНЕДЖЕР 17
A2: ПОКАЗАТЕЛИ ЭФФЕКТИВНОСТИ ПО ДНЯМ МЕСЯЦА
A3: МЕТРИКА / ДАТА | B3: 01 | C3: 02 | D3: 03 | E3: 04 | F3: 05 | G3: 06 | H3: 07 | I3: 08 | J3: 09 | K3: 10 | L3: 11 | M3: 12 | N3: 13 | O3: 14 | P3: 15 | Q3: 16 | R3: 17 | S3: 18 | T3: 19 | U3: 20 | V3: 21 | W3: 22 | X3: 23 | Y3: 24 | Z3: 25 | AA3: 26 | AB3: 27 | AC3: 28 | AD3: 29 | AE3: 30 | AF3: 31 | AG3: ИТОГО
A4: Лиды | AG4: =SUM(B4:AF4)
A5: Обработка | AG5: =SUM(B5:AF5)
A6: Не дозвон | AG6: =SUM(B6:AF6)
A7: Ожидание | AG7: =SUM(B7:AF7)
A8: Отказ | AG8: =SUM(B8:AF8)
A9: Продажа | AG9: =SUM(B9:AF9)
A10: Выручка (сом) | AG10: =SUM(B10:AF10)
A11: Конверсия % | AG11: =IF(AG4=0,0,AG9/AG4*100)
A12: Остаток (сом) | AG12: =SUM(B12:AF12)
A15: 📋 РЕЕСТР КЛИЕНТОВ - МЕНЕДЖЕР 17
A16: № | B16: ФИ Клиента | C16: Регион | D16: Телефон | E16: Цена курса (сом) | F16: Статус оплаты | G16: Дата след. оплаты | H16: Остаток (сом) | I16: Комментарий
A38: РЕЕСТР ЛИДОВ - МЕНЕДЖЕР 17
A40: № | J40: Дата платежа | K40: Комментарий
A41: 1
A42: 2
A43: 3
A44: 4
A45: 5

Sheet Mgr_18
A1: 📈 ЕЖЕДНЕВНЫЙ ОТЧЕТ - МЕНЕДЖЕР 18
A2: ПОКАЗАТЕЛИ ЭФФЕКТИВНОСТИ ПО ДНЯМ МЕСЯЦА
A3: МЕТРИКА / ДАТА | B3: 01 | C3: 02 | D3: 03 | E3: 04 | F3: 05 | G3: 06 | H3: 07 | I3: 08 | J3: 09 | K3: 10 | L3: 11 | M3: 12 | N3: 13 | O3: 14 | P3: 15 | Q3: 16 | R3: 17 | S3: 18 | T3: 19 | U3: 20 | V3: 21 | W3: 22 | X3: 23 | Y3: 24 | Z3: 25 | AA3: 26 | AB3: 27 | AC3: 28 | AD3: 29 | AE3: 30 | AF3: 31 | AG3: ИТОГО
A4: Лиды | AG4: =SUM(B4:AF4)
A5: Обработка | AG5: =SUM(B5:AF5)
A6: Не дозвон | AG6: =SUM(B6:AF6)
A7: Ожидание | AG7: =SUM(B7:AF7)
A8: Отказ | AG8: =SUM(B8:AF8)
A9: Продажа | AG9: =SUM(B9:AF9)
A10: Выручка (сом) | AG10: =SUM(B10:AF10)
A11: Конверсия % | AG11: =IF(AG4=0,0,AG9/AG4*100)
A12: Остаток (сом) | AG12: =SUM(B12:AF12)
A15: 📋 РЕЕСТР КЛИЕНТОВ - МЕНЕДЖЕР 18
A16: № | B16: ФИ Клиента | C16: Регион | D16: Телефон | E16: Цена курса (сом) | F16: Статус оплаты | G16: Дата след. оплаты | H16: Остаток (сом) | I16: Комментарий
A38: РЕЕСТР ЛИДОВ - МЕНЕДЖЕР 18
A40: № | J40: Дата платежа | K40: Комментарий
A41: 1
A42: 2
A43: 3
A44: 4
A45: 5

Sheet Mgr_19
A1: 📈 ЕЖЕДНЕВНЫЙ ОТЧЕТ - МЕНЕДЖЕР 19
A2: ПОКАЗАТЕЛИ ЭФФЕКТИВНОСТИ ПО ДНЯМ МЕСЯЦА
A3: МЕТРИКА / ДАТА | B3: 01 | C3: 02 | D3: 03 | E3: 04 | F3: 05 | G3: 06 | H3: 07 | I3: 08 | J3: 09 | K3: 10 | L3: 11 | M3: 12 | N3: 13 | O3: 14 | P3: 15 | Q3: 16 | R3: 17 | S3: 18 | T3: 19 | U3: 20 | V3: 21 | W3: 22 | X3: 23 | Y3: 24 | Z3: 25 | AA3: 26 | AB3: 27 | AC3: 28 | AD3: 29 | AE3: 30 | AF3: 31 | AG3: ИТОГО
A4: Лиды | AG4: =SUM(B4:AF4)
A5: Обработка | AG5: =SUM(B5:AF5)
A6: Не дозвон | AG6: =SUM(B6:AF6)
A7: Ожидание | AG7: =SUM(B7:AF7)
A8: Отказ | AG8: =SUM(B8:AF8)
A9: Продажа | AG9: =SUM(B9:AF9)
A10: Выручка (сом) | AG10: =SUM(B10:AF10)
A11: Конверсия % | AG11: =IF(AG4=0,0,AG9/AG4*100)
A12: Остаток (сом) | AG12: =SUM(B12:AF12)
A15: 📋 РЕЕСТР КЛИЕНТОВ - МЕНЕДЖЕР 19
A16: № | B16: ФИ Клиента | C16: Регион | D16: Телефон | E16: Цена курса (сом) | F16: Статус оплаты | G16: Дата след. оплаты | H16: Остаток (сом) | I16: Комментарий
A38: РЕЕСТР ЛИДОВ - МЕНЕДЖЕР 19
A40: № | J40: Дата платежа | K40: Комментарий
A41: 1
A42: 2
A43: 3
A44: 4
A45: 5

Sheet Mgr_20
A1: 📈 ЕЖЕДНЕВНЫЙ ОТЧЕТ - МЕНЕДЖЕР 20
A2: ПОКАЗАТЕЛИ ЭФФЕКТИВНОСТИ ПО ДНЯМ МЕСЯЦА
A3: МЕТРИКА / ДАТА | B3: 01 | C3: 02 | D3: 03 | E3: 04 | F3: 05 | G3: 06 | H3: 07 | I3: 08 | J3: 09 | K3: 10 | L3: 11 | M3: 12 | N3: 13 | O3: 14 | P3: 15 | Q3: 16 | R3: 17 | S3: 18 | T3: 19 | U3: 20 | V3: 21 | W3: 22 | X3: 23 | Y3: 24 | Z3: 25 | AA3: 26 | AB3: 27 | AC3: 28 | AD3: 29 | AE3: 30 | AF3: 31 | AG3: ИТОГО
A4: Лиды | AG4: =SUM(B4:AF4)
A5: Обработка | AG5: =SUM(B5:AF5)
A6: Не дозвон | AG6: =SUM(B6:AF6)
A7: Ожидание | AG7: =SUM(B7:AF7)
A8: Отказ | AG8: =SUM(B8:AF8)
A9: Продажа | AG9: =SUM(B9:AF9)
A10: Выручка (сом) | AG10: =SUM(B10:AF10)
A11: Конверсия % | AG11: =IF(AG4=0,0,AG9/AG4*100)
A12: Остаток (сом) | AG12: =SUM(B12:AF12)
A15: 📋 РЕЕСТР КЛИЕНТОВ - МЕНЕДЖЕР 20
A16: № | B16: ФИ Клиента | C16: Регион | D16: Телефон | E16: Цена курса (сом) | F16: Статус оплаты | G16: Дата след. оплаты | H16: Остаток (сом) | I16: Комментарий
A38: РЕЕСТР ЛИДОВ - МЕНЕДЖЕР 20
A40: № | J40: Дата платежа | K40: Комментарий
A41: 1
A42: 2
A43: 3
A44: 4
A45: 5
